{
    "version":"Sample 1.0.0",
    "model":"model.moc",
    "textures":[
        "texture_00.png"
    ],
    "expressions":[
        {
            "name":"confused",
            "file":"confused.exp.json"
        },
        {
            "name":"idle",
            "file":"idle.exp.json"
        },
        {
            "name":"joy",
            "file":"joy.exp.json"
        },
        {
            "name":"sad",
            "file":"sad.exp.json"
        }
    ],
    "motions":{
        "attack":[
            {
                "file":"c480_01_attack.mtn",
                "fade_in":0,
                "fade_out":0
            }
        ],
        "banner":[
            {
                "file":"c480_01_banner.mtn",
                "fade_in":0,
                "fade_out":0
            }
        ],
        "hit":[
            {
                "file":"c480_01_hit.mtn",
                "fade_in":0,
                "fade_out":0
            }
        ],
        "idle":[
            {
                "file":"c480_01_idle.mtn",
                "fade_in":0,
                "fade_out":0
            }
        ]
    }
}